braid_db/__init__.py
braid_db/brad_db_sqlite.py
braid_db/braid-db.sql
braid_db/braid_db.py
braid_db/braid_db_sqlite.py
braid_db/client.py
braid_db/db_func.py
braid_db/db_tools.py
braid_db/db_tools_mpi.py
braid_db/funcx/__init__.py
braid_db/funcx/endpoint_config.py
braid_db/funcx/funcx_main.py
braid_db/gen_tools.py
braid_db/log_tools.py
braid_db/models/__init__.py
braid_db/models/api/__init__.py
braid_db/models/api/api_models.py
braid_db/models/braid_models.py
braid_db/server.py
braid_db/service/viz/dot_graphing.py
braid_db/service/viz/mermaid_graphing.py
braid_db/service/viz/template.html
braid_db/tools/.flake8
braid_db/tools/__init__.py
braid_db/tools/db-create.py
braid_db/tools/db_create.py
braid_db/tools/db_print.py
braid_db/tools/record_invalidate.py
workflows/BraggNN/workflow.py
workflows/BraggNN/workflow.sh
workflows/CTSegNet/.flake8
workflows/CTSegNet/workflow.py
workflows/CTSegNet/workflow.sh
workflows/SLAC/workflow.py
workflows/SLAC/workflow.sh
workflows/SSX/workflow.py
workflows/SSX/workflow.sh
workflows/mascot/.flake8
workflows/mascot/.gitignore
workflows/mascot/mascot.dot
workflows/mascot/mascot.html
workflows/mascot/mascot.png
workflows/mascot/workflow.py
workflows/mascot/workflow.sh
braid_db-0.1.0a1.dist-info/METADATA
braid_db-0.1.0a1.dist-info/WHEEL
braid_db-0.1.0a1.dist-info/entry_points.txt
braid_db-0.1.0a1.dist-info/RECORD
