Metadata-Version: 2.1
Name: braid-db
Version: 0.1.0a1
Summary: The Braid Project Provenance DB
Home-page: https://github.com/ANL-Braid/DB
License: LGPL-3.0-or-later
Author: Justin Wozniak
Author-email: woz@anl.gov
Requires-Python: >=3.9,<4.0
Classifier: License :: OSI Approved :: GNU Lesser General Public License v3 or later (LGPLv3+)
Classifier: Programming Language :: Python :: 3
Classifier: Programming Language :: Python :: 3.9
Classifier: Programming Language :: Python :: 3.10
Classifier: Programming Language :: Python :: 3.11
Requires-Dist: SQLAlchemy (==1.4.35)
Requires-Dist: funcx (>=1,<2)
Requires-Dist: funcx-endpoint (>=1,<2)
Requires-Dist: simpleeval (>=0.9,<0.10)
Requires-Dist: sqlmodel (>=0,<1)
Project-URL: Documentation, https://braid-db.readthedocs.io/en/main/
Project-URL: Repository, https://github.com/ANL-Braid/DB
